ddpg/__init__.py
ddpg/actor_critic.py
ddpg/buffer.py
ddpg/ddpg.py
DDPG_TF-2.0.3.dist-info/METADATA
DDPG_TF-2.0.3.dist-info/WHEEL
DDPG_TF-2.0.3.dist-info/top_level.txt
DDPG_TF-2.0.3.dist-info/RECORD
