Metadata-Version: 2.1
Name: DDPG-TF
Version: 2.0.3
Summary: DDPG implimentaion in Tensorflow-2.0 
Home-page: https://github.com/Dekki-Aero/DDPG
Author: Dekki
Author-email: dekkiaero@gmail.com
License: UNKNOWN
Keywords: Deep Determnistic policy gradient,Actor Critic,Reinforcement Learning,DDPG
Platform: UNKNOWN
Requires-Dist: tensorflow (==2.0)
Requires-Dist: gym
Requires-Dist: numpy
Requires-Dist: matplotlib
